MMP-CloudPointFusion/Scan.py
MMP-CloudPointFusion/Sequence.py
MMP-CloudPointFusion/__init__.py
MMP-CloudPointFusion/fusion.py
MMP_CloudPointFusion/Scan.py
MMP_CloudPointFusion/Sequence.py
MMP_CloudPointFusion/__init__.py
MMP_CloudPointFusion/fusion.py
NBIA_Fusion-0.2.dist-info/METADATA
NBIA_Fusion-0.2.dist-info/WHEEL
NBIA_Fusion-0.2.dist-info/top_level.txt
NBIA_Fusion-0.2.dist-info/RECORD
