Metadata-Version: 2.1
Name: NBIA-Fusion
Version: 0.2
